topsis/101903150.py
topsis_ADITYA_101903150-1.0.0.dist-info/LICENSE
topsis_ADITYA_101903150-1.0.0.dist-info/METADATA
topsis_ADITYA_101903150-1.0.0.dist-info/WHEEL
topsis_ADITYA_101903150-1.0.0.dist-info/top_level.txt
topsis_ADITYA_101903150-1.0.0.dist-info/RECORD
